[
  {
    "id": "ocd-person/0c6a7bcf-e990-41a0-b59c-923f05771880",
    "name": "Adam Bird",
    "firstName": "Adam",
    "lastName": "Bird",
    "chamber": "lower",
    "district": "63",
    "party": "Republican",
    "email": "rep63@ohiohouse.gov",
    "phone": "614-644-6034",
    "photoUrl": "https://www.legislature.ohio.gov/assets/people/adam-c-bird/headshots/thumbnails/medium/adam-c-bird-january-2023-headshot_medium.jpg",
    "website": "https://ohiohouse.gov/adam-c-bird",
    "office": "77 S. High St. 14th Floor, Columbus, OH 43215"
  },
  {
    "id": "ocd-person/78912d95-3dac-4487-810a-74be41508ebb",
    "name": "Adam Holmes",
    "firstName": "Adam",
    "lastName": "Holmes",
    "chamber": "lower",
    "district": "97",
    "party": "Republican",
    "email": "rep97@ohiohouse.gov",
    "phone": "614-644-6014",
    "photoUrl": "https://www.legislature.ohio.gov/assets/people/adam-holmes/headshots/thumbnails/medium/adam-holmes-january-2021-headshot_medium.jpg",
    "website": "https://ohiohouse.gov/adam-holmes",
    "office": "77 S. High St. 13th Floor, Columbus, OH 43215"
  },
  {
    "id": "ocd-person/b04e2962-e7c6-46b8-9a99-d7a6d3a32717",
    "name": "Adam Mathews",
    "firstName": "Adam",
    "lastName": "Mathews",
    "chamber": "lower",
    "district": "56",
    "party": "Republican",
    "email": "rep56@ohiohouse.gov",
    "phone": "614-644-6027",
    "photoUrl": "https://www.legislature.ohio.gov/assets/people/adam-mathews/headshots/thumbnails/medium/adam-mathews-january-2023-headshot_medium.jpg",
    "website": "https://www.ohiohouse.gov/members/adam-mathews",
    "office": "77 S. High St. 13th Floor, Columbus, OH 43215"
  },
  {
    "id": "ocd-person/6a1fc3b1-ebfd-47b7-adec-ddcd84d137c9",
    "name": "Al Cutrona",
    "firstName": "Al",
    "lastName": "Cutrona",
    "chamber": "upper",
    "district": "33",
    "party": "Republican",
    "email": "sd33@ohiosenate.gov",
    "phone": "614-466-8285",
    "photoUrl": "https://www.legislature.ohio.gov/assets/people/al-cutrona/headshots/thumbnails/medium/al-cutrona-february-2023-headshot_medium.jpg",
    "website": "https://ohiohouse.gov/al-cutrona",
    "office": "Room 41, Statehouse, 1 Capitol Square Ground Floor, Columbus, OH 43215"
  },
  {
    "id": "ocd-person/debec71d-fcfb-4422-9c9e-c6a8709cbb3a",
    "name": "Al Landis",
    "firstName": "Al",
    "lastName": "Landis",
    "chamber": "upper",
    "district": "31",
    "party": "Republican",
    "email": "sd31@ohiosenate.gov",
    "phone": "614-466-5838",
    "photoUrl": "https://www.legislature.ohio.gov/assets/people/al-landis/headshots/thumbnails/medium/al-landis-may-2023-headshot_medium.jpg",
    "website": "https://ohiosenate.gov/members/al-landis",
    "office": "Room 38, Statehouse, 1 Capitol Square Ground Floor, Columbus, OH 43215"
  },
  {
    "id": "ocd-person/07c054e9-9a51-41b2-994a-8f63b0148d07",
    "name": "Andrea White",
    "firstName": "Andrea",
    "lastName": "White",
    "chamber": "lower",
    "district": "36",
    "party": "Republican",
    "email": "rep36@ohiohouse.gov",
    "phone": "614-644-6008",
    "photoUrl": "https://www.legislature.ohio.gov/assets/people/andrea-white/headshots/thumbnails/medium/andrea-white-march-2023-headshot_medium.jpg",
    "website": "https://ohiohouse.gov/andrea-white",
    "office": "77 S. High St. 11th Floor, Columbus, OH 43215"
  },
  {
    "id": "ocd-person/c61c8eaf-1de9-419d-a5dc-c96787315578",
    "name": "Andrew Brenner",
    "firstName": "Andrew",
    "lastName": "Brenner",
    "chamber": "upper",
    "district": "19",
    "party": "Republican",
    "email": "sd19@ohiosenate.gov",
    "phone": "614-466-8086",
    "photoUrl": "https://www.legislature.ohio.gov/assets/people/andrew-o-brenner/headshots/thumbnails/medium/andrew-o-brenner-may-2023-headshot_medium.jpg",
    "website": "https://www.ohiosenate.gov/members/andrew-o-brenner",
    "office": "Room 140, Statehouse, 1 Capitol Square First Floor, Columbus, OH 43215"
  },
  {
    "id": "ocd-person/4ed8184a-01ff-4bdc-a06c-cbf8b4c73fd6",
    "name": "Angie King",
    "firstName": "Angie",
    "lastName": "King",
    "chamber": "lower",
    "district": "84",
    "party": "Republican",
    "email": "rep84@ohiohouse.gov",
    "phone": "614-466-9624",
    "photoUrl": "https://www.legislature.ohio.gov/assets/people/angela-n-king/headshots/thumbnails/medium/angela-n-king-january-2023-headshot_medium.jpg",
    "website": "https://www.ohiohouse.gov/members/angela-n-king",
    "office": "77 S. High St. 11th Floor, Columbus, OH 43215"
  },
  {
    "id": "ocd-person/3bfe0748-5423-4fcf-9962-905d2b747f23",
    "name": "Anita Somani",
    "firstName": "Anita",
    "lastName": "Somani",
    "chamber": "lower",
    "district": "8",
    "party": "Democratic",
    "email": "rep08@ohiohouse.gov",
    "phone": "614-466-5358",
    "photoUrl": "https://www.legislature.ohio.gov/assets/people/anita-somani/headshots/thumbnails/medium/anita-somani-january-2023-headshot_medium.jpg",
    "website": "https://www.ohiohouse.gov/members/anita-somani",
    "office": "77 S. High St. 10th Floor, Columbus, OH 43215"
  },
  {
    "id": "ocd-person/6d39391d-7068-4ad3-866d-4ee59890ce6e",
    "name": "Ashley Bryant Bailey",
    "firstName": "Ashley",
    "lastName": "Bryant Bailey",
    "chamber": "lower",
    "district": "26",
    "party": "Democratic",
    "email": "rep26@ohiohouse.gov",
    "phone": "614-466-1308",
    "website": "https://ohiohouse.gov/members/ashley-bryant-bailey",
    "office": "77 S. High St. 10th Floor, Columbus, OH 43215"
  },
  {
    "id": "ocd-person/550986e6-b595-4fa8-9424-8e09327cf060",
    "name": "Bernie Willis",
    "firstName": "Bernie",
    "lastName": "Willis",
    "chamber": "lower",
    "district": "74",
    "party": "Republican",
    "email": "rep74@ohiohouse.gov",
    "phone": "614-466-2038",
    "photoUrl": "https://www.legislature.ohio.gov/assets/people/bernard-willis/headshots/thumbnails/medium/bernard-willis-february-2023-headshot_medium.jpg",
    "website": "https://www.ohiohouse.gov/members/bernard-willis",
    "office": "77 S. High St. 13th Floor, Columbus, OH 43215"
  },
  {
    "id": "ocd-person/dc1a25bf-ebf6-4d5c-b5c3-32f9fdb8b2ed",
    "name": "Beryl Piccolantonio",
    "firstName": "Beryl",
    "lastName": "Piccolantonio",
    "chamber": "lower",
    "district": "4",
    "party": "Democratic",
    "email": "rep04@ohiohouse.gov",
    "phone": "614-466-4847",
    "website": "https://ohiohouse.gov/members/beryl-piccolantonio",
    "office": "77 S. High St. 14th Floor, Columbus, OH 43215"
  },
  {
    "id": "ocd-person/de0a6483-7c16-43e1-a76b-c0cc98a9d7ed",
    "name": "Beth Lear",
    "firstName": "Beth",
    "lastName": "Lear",
    "chamber": "lower",
    "district": "61",
    "party": "Republican",
    "email": "rep61@ohiohouse.gov",
    "phone": "614-466-1431",
    "photoUrl": "https://www.legislature.ohio.gov/assets/people/beth-lear/headshots/thumbnails/medium/beth-lear-january-2023-headshot_medium.jpg",
    "website": "https://www.ohiohouse.gov/members/beth-lear",
    "office": "77 S. High St. 12th Floor, Columbus, OH 43215"
  },
  {
    "id": "ocd-person/2d01ff0c-25a8-49a2-b571-ab3a7866fcf2",
    "name": "Beth Liston",
    "firstName": "Beth",
    "lastName": "Liston",
    "chamber": "upper",
    "district": "16",
    "party": "Democratic",
    "email": "sd16@ohiosenate.gov",
    "phone": "614-466-5981",
    "photoUrl": "https://www.legislature.ohio.gov/assets/people/beth-liston/headshots/thumbnails/medium/beth-liston-november-2023-headshot_medium.jpg",
    "website": "https://ohiohouse.gov/beth-liston",
    "office": "Room 51, Statehouse, 1 Capitol Square Ground Floor, Columbus, OH 43215"
  },
  {
    "id": "ocd-person/10733ff7-ee19-4e86-9b5e-65619ddbf7bf",
    "name": "Bill Reineke",
    "firstName": "Bill",
    "lastName": "Reineke",
    "chamber": "upper",
    "district": "26",
    "party": "Republican",
    "email": "sd26@ohiosenate.gov",
    "phone": "614-466-8049",
    "photoUrl": "https://www.legislature.ohio.gov/assets/people/bill-reineke/headshots/thumbnails/medium/bill-reineke-may-2023-headshot_medium.jpg",
    "website": "https://www.ohiohouse.gov/bill-reineke",
    "office": "Room 220, Statehouse, 1 Capitol Square Second Floor, Columbus, OH 43215"
  },
  {
    "id": "ocd-person/4cece9f3-e252-438b-8255-a2150a4ed599",
    "name": "Bill Roemer",
    "firstName": "Bill",
    "lastName": "Roemer",
    "chamber": "lower",
    "district": "31",
    "party": "Republican",
    "email": "rep31@ohiohouse.gov",
    "phone": "614-644-5085",
    "photoUrl": "https://www.legislature.ohio.gov/assets/people/bill-roemer/headshots/thumbnails/medium/bill-roemer-january-2019-headshot_medium.jpg",
    "website": "https://ohiohouse.gov/bill-roemer",
    "office": "77 S. High St. 11th Floor, Columbus, OH 43215"
  },
  {
    "id": "ocd-person/cdc9f705-514e-4445-ac17-9aeac8f67e97",
    "name": "Bob Peterson",
    "firstName": "Bob",
    "lastName": "Peterson",
    "chamber": "lower",
    "district": "91",
    "party": "Republican",
    "email": "rep91@ohiohouse.gov",
    "phone": "614-466-3506",
    "photoUrl": "https://www.legislature.ohio.gov/assets/people/bob-peterson/headshots/thumbnails/medium/bob-peterson-november-2023-headshot_medium.jpg",
    "website": "https://ohiohouse.gov/members/bob-peterson",
    "office": "77 S. High St. 11th Floor, Columbus, OH 43215"
  },
  {
    "id": "ocd-person/1895e223-ba42-4e25-8cd0-915ca5cc2829",
    "name": "Brian Lampton",
    "firstName": "Brian",
    "lastName": "Lampton",
    "chamber": "lower",
    "district": "70",
    "party": "Republican",
    "email": "rep70@ohiohouse.gov",
    "phone": "614-644-6020",
    "photoUrl": "https://www.legislature.ohio.gov/assets/people/brian-e-lampton/headshots/thumbnails/medium/brian-e-lampton-january-2023-headshot_medium.jpg",
    "website": "https://ohiohouse.gov/brian-e-lampton",
    "office": "77 S. High St. 13th Floor, Columbus, OH 43215"
  },
  {
    "id": "ocd-person/a3ccce64-ea28-47dc-8bab-3af6ed2dd860",
    "name": "Brian Lorenz",
    "firstName": "Brian",
    "lastName": "Lorenz",
    "chamber": "lower",
    "district": "60",
    "party": "Republican",
    "email": "rep60@ohiohouse.gov",
    "phone": "614-644-6711",
    "photoUrl": "https://www.legislature.ohio.gov/assets/people/brian-lorenz/headshots/thumbnails/medium/brian-lorenz-november-2023-headshot_medium.jpg",
    "website": "https://ohiohouse.gov/members/brian-lorenz",
    "office": "77 S. High St. 11th Floor, Columbus, OH 43215"
  },
  {
    "id": "ocd-person/eb5ff860-2126-4ac5-8267-9d2d924c3967",
    "name": "Brian Chavez",
    "firstName": "Brian",
    "lastName": "Chavez",
    "chamber": "upper",
    "district": "30",
    "party": "Republican",
    "email": "sd30@ohiosenate.gov",
    "phone": "614-466-6508",
    "photoUrl": "https://www.legislature.ohio.gov/assets/people/brian-m-chavez/headshots/thumbnails/medium/brian-m-chavez-december-2023-headshot-10001385_medium.jpg",
    "website": "https://www.ohiosenate.gov/members/brian-m-chavez",
    "office": "Room 34, Statehouse, 1 Capitol Square Ground Floor, Columbus, OH 43215"
  },
  {
    "id": "ocd-person/f4e6c51a-89bd-4841-848b-b1097fd3fc9d",
    "name": "Brian Stewart",
    "firstName": "Brian",
    "lastName": "Stewart",
    "chamber": "lower",
    "district": "12",
    "party": "Republican",
    "email": "rep12@ohiohouse.gov",
    "phone": "614-466-1464",
    "photoUrl": "https://www.legislature.ohio.gov/assets/people/brian-stewart/headshots/thumbnails/medium/brian-stewart-november-2023-headshot_medium.jpg",
    "website": "https://ohiohouse.gov/brian-stewart",
    "office": "77 S. High St. 13th Floor, Columbus, OH 43215"
  },
  {
    "id": "ocd-person/2481dfc7-d260-49c6-9461-9e6048ed27a2",
    "name": "Bride Sweeney",
    "firstName": "Bride",
    "lastName": "Sweeney",
    "chamber": "lower",
    "district": "16",
    "party": "Democratic",
    "email": "rep16@ohiohouse.gov",
    "phone": "614-466-3350",
    "photoUrl": "https://www.legislature.ohio.gov/assets/people/bride-rose-sweeney/headshots/thumbnails/medium/bride-rose-sweeney-january-2019-headshot_medium.jpg",
    "website": "https://ohiohouse.gov/bride-rose-sweeney",
    "office": "77 S. High St. 10th Floor, Columbus, OH 43215"
  },
  {
    "id": "ocd-person/c58b6767-730d-4486-a08e-462ea3af3bfe",
    "name": "Allison Russo",
    "firstName": "Allison",
    "lastName": "Russo",
    "chamber": "lower",
    "district": "7",
    "party": "Democratic",
    "email": "rep07@ohiohouse.gov",
    "phone": "614-466-8012",
    "photoUrl": "https://www.legislature.ohio.gov/assets/people/c-allison-russo/headshots/thumbnails/medium/c-allison-russo-january-2021-headshot_medium.jpg",
    "website": "https://ohiohouse.gov/c-allison-russo",
    "office": "77 S. High St. 10th Floor, Columbus, OH 43215"
  },
  {
    "id": "ocd-person/d7949531-f267-4e99-9611-87b3ec3e04ac",
    "name": "Casey Weinstein",
    "firstName": "Casey",
    "lastName": "Weinstein",
    "chamber": "upper",
    "district": "28",
    "party": "Democratic",
    "email": "sd28@ohiosenate.gov",
    "phone": "614-466-7041",
    "photoUrl": "https://www.legislature.ohio.gov/assets/people/casey-weinstein/headshots/thumbnails/medium/casey-weinstein-january-2023-headshot_medium.jpg",
    "website": "https://ohiohouse.gov/casey-weinstein",
    "office": "Room 50, Statehouse, 1 Capitol Square Ground Floor, Columbus, OH 43215"
  },
  {
    "id": "ocd-person/94ba65dd-57c5-4ab0-b607-5e310d50cae0",
    "name": "Catherine Ingram",
    "firstName": "Catherine",
    "lastName": "Ingram",
    "chamber": "upper",
    "district": "9",
    "party": "Democratic",
    "email": "sd09@ohiosenate.gov",
    "phone": "614-466-5980",
    "photoUrl": "https://www.legislature.ohio.gov/assets/people/catherine-d-ingram/headshots/thumbnails/medium/catherine-d-ingram-may-2023-headshot_medium.jpg",
    "website": "https://ohiohouse.gov/catherine-d-ingram",
    "office": "Room 56, Statehouse, 1 Capitol Square Ground Floor, Columbus, OH 43215"
  },
  {
    "id": "ocd-person/5ba7ae7d-2f10-42b7-8784-8e734507ce33",
    "name": "Cecil Thomas",
    "firstName": "Cecil",
    "lastName": "Thomas",
    "chamber": "lower",
    "district": "25",
    "party": "Democratic",
    "email": "rep25@ohiohouse.gov",
    "phone": "614-466-1645",
    "photoUrl": "https://www.legislature.ohio.gov/assets/people/cecil-thomas/headshots/thumbnails/medium/cecil-thomas-january-2023-headshot_medium.jpg",
    "website": "https://ohiohouse.gov/members/cecil-thomas",
    "office": "77 S. High St. 10th Floor, Columbus, OH 43215"
  },
  {
    "id": "ocd-person/80daf159-0742-4a3f-9575-e6492155c911",
    "name": "Chris Glassburn",
    "firstName": "Chris",
    "lastName": "Glassburn",
    "chamber": "lower",
    "district": "15",
    "party": "Democratic",
    "email": "rep15@ohiohouse.gov",
    "phone": "614-466-3100",
    "photoUrl": "https://img1.wsimg.com/isteam/ip/fdba7286-8a27-4b98-a8ec-557eff11bd3a/IMG_3635.jpg/:/cr=t:5.66%25,l:0%25,w:94.34%25,h:94.34%25/rs=w:365,h:487,cg:true,m",
    "website": "https://ohiohouse.gov/members/chris-glassburn",
    "office": "77 S. High St. 10th Floor, Columbus, OH 43215"
  },
  {
    "id": "ocd-person/b76c6e1e-8b9d-42bf-b615-73270b132773",
    "name": "Christine Cockley",
    "firstName": "Christine",
    "lastName": "Cockley",
    "chamber": "lower",
    "district": "6",
    "party": "Democratic",
    "email": "rep06@ohiohouse.gov",
    "phone": "614-644-6005",
    "photoUrl": "https://s3.amazonaws.com/ballotpedia-api4/files/thumbs/200/300/ChristineCockley2024.jpg",
    "website": "https://ohiohouse.gov/members/christine-cockley",
    "office": "77 S. High St. 10th Floor, Columbus, OH 43215"
  },
  {
    "id": "ocd-person/9ae0194c-0f5b-44c6-b84f-a0ec4d3f3a61",
    "name": "Cindy Abrams",
    "firstName": "Cindy",
    "lastName": "Abrams",
    "chamber": "lower",
    "district": "29",
    "party": "Republican",
    "email": "rep29@ohiohouse.gov",
    "phone": "614-466-9091",
    "photoUrl": "https://www.legislature.ohio.gov/assets/people/cindy-abrams/headshots/thumbnails/medium/cindy-abrams-january-2023-headshot_medium.jpg",
    "website": "https://ohiohouse.gov/cindy-abrams",
    "office": "77 S. High St. 13th Floor, Columbus, OH 43215"
  },
  {
    "id": "ocd-person/aede29b6-7798-45b7-8401-5004cf1c29f9",
    "name": "Crystal Lett",
    "firstName": "Crystal",
    "lastName": "Lett",
    "chamber": "lower",
    "district": "11",
    "party": "Democratic",
    "email": "rep11@ohiohouse.gov",
    "phone": "614-644-6030",
    "photoUrl": "https://i0.wp.com/lettsgoohio.com/wp-content/uploads/2024/07/Meet-Crystal.webp?resize=674%2C1024&ssl=1",
    "website": "https://ohiohouse.gov/members/crystal-lett",
    "office": "77 S. High St. 10th Floor, Columbus, OH 43215"
  },
  {
    "id": "ocd-person/cb2ddd04-e5b0-4c96-b217-d02b732eb896",
    "name": "D.J. Swearingen",
    "firstName": "D.J.",
    "lastName": "Swearingen",
    "chamber": "lower",
    "district": "89",
    "party": "Republican",
    "email": "rep89@ohiohouse.gov",
    "phone": "614-644-6011",
    "photoUrl": "https://www.legislature.ohio.gov/assets/people/d-j-swearingen/headshots/thumbnails/medium/d-j-swearingen-january-2021-headshot_medium.jpg",
    "website": "https://ohiohouse.gov/d-j-swearingen",
    "office": "77 S. High St. 13th Floor, Columbus, OH 43215"
  },
  {
    "id": "ocd-person/1cc15373-6101-48fb-9597-d731c115eb70",
    "name": "Dani Isaacsohn",
    "firstName": "Dani",
    "lastName": "Isaacsohn",
    "chamber": "lower",
    "district": "24",
    "party": "Democratic",
    "email": "rep24@ohiohouse.gov",
    "phone": "614-466-5786",
    "photoUrl": "https://www.legislature.ohio.gov/assets/people/dani-isaacsohn/headshots/thumbnails/medium/dani-isaacsohn-april-2023-headshot_medium.jpg",
    "website": "https://www.ohiohouse.gov/members/dani-isaacsohn",
    "office": "77 S. High St. 14th Floor, Columbus, OH 43215"
  },
  {
    "id": "ocd-person/04d4dc4f-a38a-4d50-8962-ea961550b2ff",
    "name": "Dan Troy",
    "firstName": "Dan",
    "lastName": "Troy",
    "chamber": "lower",
    "district": "23",
    "party": "Democratic",
    "email": "rep23@ohiohouse.gov",
    "phone": "614-466-7251",
    "photoUrl": "https://www.legislature.ohio.gov/assets/people/daniel-p-troy/headshots/thumbnails/medium/daniel-p-troy-january-2021-headshot_medium.jpg",
    "website": "https://ohiohouse.gov/daniel-p-troy",
    "office": "77 S. High St. 10th Floor, Columbus, OH 43215"
  },
  {
    "id": "ocd-person/a75181f0-f0e8-4af3-aefd-6cc08543af1a",
    "name": "Darnell Brewer",
    "firstName": "Darnell",
    "lastName": "Brewer",
    "chamber": "lower",
    "district": "22",
    "party": "Democratic",
    "email": "rep22@ohiohouse.gov",
    "phone": "614-466-1414",
    "photoUrl": "https://www.legislature.ohio.gov/assets/people/darnell-t-brewer/headshots/thumbnails/medium/darnell-t-brewer-january-2023-headshot_medium.jpg",
    "website": "https://ohiohouse.gov/members/darnell-t-brewer",
    "office": "77 S. High St. 10th Floor, Columbus, OH 43215"
  },
  {
    "id": "ocd-person/170299dd-f2e4-463e-8b8b-ea3b75946120",
    "name": "David Thomas",
    "firstName": "David",
    "lastName": "Thomas",
    "chamber": "lower",
    "district": "65",
    "party": "Republican",
    "email": "rep65@ohiohouse.gov",
    "phone": "614-466-3488",
    "photoUrl": "https://s3.amazonaws.com/ballotpedia-api4/files/thumbs/200/300/DavidThomas2024.jpg",
    "website": "https://ohiohouse.gov/members/david-thomas",
    "office": "77 S. High St. 11th Floor, Columbus, OH 43215"
  },
  {
    "id": "ocd-person/826530cc-f105-42c8-96db-e5ff7d1a966d",
    "name": "Derrick Hall",
    "firstName": "Derrick",
    "lastName": "Hall",
    "chamber": "lower",
    "district": "34",
    "party": "Democratic",
    "email": "rep34@ohiohouse.gov",
    "phone": "614-466-1177",
    "photoUrl": "https://derrickhallforohio.com/wp-content/uploads/2024/01/derrick-hall.jpg",
    "website": "https://ohiohouse.gov/members/derrick-hall",
    "office": "77 S. High St. 10th Floor, Columbus, OH 43215"
  },
  {
    "id": "ocd-person/86352961-5ebc-408a-9f16-8d801c7476dc",
    "name": "Desireè Tims",
    "firstName": "Desireè",
    "lastName": "Tims",
    "chamber": "lower",
    "district": "38",
    "party": "Democratic",
    "email": "rep38@ohiohouse.gov",
    "phone": "614-466-1607",
    "photoUrl": "https://images.squarespace-cdn.com/content/v1/651c6aab7b083a0ae328c9b0/bdc196f5-d426-4103-bd2c-a29517a8e9cf/headshot+state+rep.JPG?format=500w",
    "website": "https://ohiohouse.gov/members/desiree-tims",
    "office": "77 S. High St. 10th Floor, Columbus, OH 43215"
  },
  {
    "id": "ocd-person/deed175e-5c44-48f0-b2c0-baa342b2baf1",
    "name": "Diane Mullins",
    "firstName": "Diane",
    "lastName": "Mullins",
    "chamber": "lower",
    "district": "47",
    "party": "Republican",
    "email": "rep47@ohiohouse.gov",
    "phone": "614-644-6721",
    "photoUrl": "https://assets.civicengine.com/uploads/candidate/headshot/401180/401180.jpg",
    "website": "https://ohiohouse.gov/members/diane-mullins",
    "office": "77 S. High St. 11th Floor, Columbus, OH 43215"
  },
  {
    "id": "ocd-person/74c1210d-fb56-4522-8d3a-0a2bb08c972b",
    "name": "Dontavius Jarrells",
    "firstName": "Dontavius",
    "lastName": "Jarrells",
    "chamber": "lower",
    "district": "1",
    "party": "Democratic",
    "email": "rep01@ohiohouse.gov",
    "phone": "614-466-5343",
    "photoUrl": "https://www.legislature.ohio.gov/assets/people/dontavius-l-jarrells/headshots/thumbnails/medium/dontavius-l-jarrells-january-2021-headshot_medium.jpg",
    "website": "https://ohiohouse.gov/dontavius-l-jarrells",
    "office": "77 S. High St. 14th Floor, Columbus, OH 43215"
  },
  {
    "id": "ocd-person/bfe003c4-6a28-46d6-b831-07bfe8662926",
    "name": "Elgin Rogers",
    "firstName": "Elgin",
    "lastName": "Rogers",
    "chamber": "lower",
    "district": "42",
    "party": "Democratic",
    "email": "rep42@ohiohouse.gov",
    "phone": "614-466-1401",
    "photoUrl": "https://www.legislature.ohio.gov/assets/people/elgin-rogers-jr/headshots/thumbnails/medium/elgin-rogers-jr-november-2022-headshot_medium.jpg",
    "website": "https://ohiohouse.gov/members/elgin-rogers-jr",
    "office": "77 S. High St. 10th Floor, Columbus, OH 43215"
  },
  {
    "id": "ocd-person/1ebfe182-1b49-4e69-b7f3-2fd528c70d73",
    "name": "Eric Synenberg",
    "firstName": "Eric",
    "lastName": "Synenberg",
    "chamber": "lower",
    "district": "21",
    "party": "Democratic",
    "email": "rep21@ohiohouse.gov",
    "phone": "614-644-5079",
    "photoUrl": "https://synenberg.com/wp-content/uploads/2018/07/synenberg-eric-e1532726812589.jpg",
    "website": "https://ohiohouse.gov/members/eric-synenberg",
    "office": "77 S. High St. 10th Floor, Columbus, OH 43215"
  },
  {
    "id": "ocd-person/ab851536-a9e6-45d7-b2fe-fad70f5acf07",
    "name": "Erika White",
    "firstName": "Erika",
    "lastName": "White",
    "chamber": "lower",
    "district": "41",
    "party": "Democratic",
    "email": "rep41@ohiohouse.gov",
    "phone": "614-466-1731",
    "photoUrl": "https://i0.wp.com/erikaforohio.org/wp-content/uploads/2024/06/Erika_2024_enhanced.png?fit=600%2C742&ssl=1",
    "website": "https://ohiohouse.gov/members/erika-white",
    "office": "77 S. High St. 10th Floor, Columbus, OH 43215"
  },
  {
    "id": "ocd-person/04e3c98a-4ede-4501-b914-4fa13fbad194",
    "name": "Gary Click",
    "firstName": "Gary",
    "lastName": "Click",
    "chamber": "lower",
    "district": "88",
    "party": "Republican",
    "email": "rep88@ohiohouse.gov",
    "phone": "614-466-1374",
    "photoUrl": "https://www.legislature.ohio.gov/assets/people/gary-click/headshots/thumbnails/medium/gary-click-january-2023-headshot_medium.jpg",
    "website": "https://ohiohouse.gov/gary-click",
    "office": "77 S. High St. 11th Floor, Columbus, OH 43215"
  },
  {
    "id": "ocd-person/b29aadca-f2da-4f09-8a1d-7aa328768507",
    "name": "Gayle Manning",
    "firstName": "Gayle",
    "lastName": "Manning",
    "chamber": "lower",
    "district": "52",
    "party": "Republican",
    "email": "rep52@ohiohouse.gov",
    "phone": "614-644-5076",
    "photoUrl": "https://www.legislature.ohio.gov/assets/people/gayle-manning/headshots/thumbnails/medium/gayle-manning-january-2019-headshot_medium.jpg",
    "website": "https://ohiohouse.gov/gayle-manning",
    "office": "77 S. High St. 14th Floor, Columbus, OH 43215"
  },
  {
    "id": "ocd-person/445d3fc7-d9a5-48d8-8869-f023aa274ae7",
    "name": "George Lang",
    "firstName": "George",
    "lastName": "Lang",
    "chamber": "upper",
    "district": "4",
    "party": "Republican",
    "email": "sd04@ohiosenate.gov",
    "phone": "614-466-8072",
    "photoUrl": "https://www.legislature.ohio.gov/assets/people/george-f-lang/headshots/thumbnails/medium/george-f-lang-may-2023-headshot_medium.jpg",
    "website": "https://www.ohiohouse.gov/george-f-lang",
    "office": "Room 129, Statehouse, 1 Capitol Square First Floor, Columbus, OH 43215"
  },
  {
    "id": "ocd-person/82dd3548-078a-41a8-8c5b-6c652d88d0d2",
    "name": "Haraz Ghanbari",
    "firstName": "Haraz",
    "lastName": "Ghanbari",
    "chamber": "lower",
    "district": "75",
    "party": "Republican",
    "email": "rep75@ohiohouse.gov",
    "phone": "614-466-8104",
    "photoUrl": "https://www.legislature.ohio.gov/assets/people/haraz-n-ghanbari/headshots/thumbnails/medium/haraz-n-ghanbari-november-2023-headshot_medium.jpg",
    "website": "https://ohiohouse.gov/haraz-n-ghanbari",
    "office": "77 S. High St. 13th Floor, Columbus, OH 43215"
  },
  {
    "id": "ocd-person/ed858ef9-97dc-4be8-97ab-006ea96923ae",
    "name": "Hearcel Craig",
    "firstName": "Hearcel",
    "lastName": "Craig",
    "chamber": "upper",
    "district": "15",
    "party": "Democratic",
    "email": "sd15@ohiosenate.gov",
    "phone": "614-466-5131",
    "photoUrl": "https://www.legislature.ohio.gov/assets/people/hearcel-f-craig/headshots/thumbnails/medium/hearcel-f-craig-may-2023-headshot_medium.jpg",
    "website": "https://www.ohiosenate.gov/members/hearcel-f-craig",
    "office": "Room 228, Statehouse, 1 Capitol Square Second Floor, Columbus, OH 43215"
  },
  {
    "id": "ocd-person/098614cd-1972-4b98-ade6-4f5fa7cefe5b",
    "name": "Heidi Workman",
    "firstName": "Heidi",
    "lastName": "Workman",
    "chamber": "lower",
    "district": "72",
    "party": "Republican",
    "email": "rep72@ohiohouse.gov",
    "phone": "614-466-2004",
    "photoUrl": "https://www.record-courier.com/gcdn/authoring/authoring-images/2024/03/05/NREC/72855871007-heidi-workman.jpg?width=412&height=872&fit=crop&format=pjpg&auto=webp",
    "website": "https://ohiohouse.gov/members/heidi-workman",
    "office": "77 S. High St. 11th Floor, Columbus, OH 43215"
  },
  {
    "id": "ocd-person/ed31c4e5-e835-4c4c-9352-217f5dcf1037",
    "name": "Ismail Mohamed",
    "firstName": "Ismail",
    "lastName": "Mohamed",
    "chamber": "lower",
    "district": "3",
    "party": "Democratic",
    "email": "rep03@ohiohouse.gov",
    "phone": "614-466-1896",
    "photoUrl": "https://www.legislature.ohio.gov/assets/people/ismail-mohamed/headshots/thumbnails/medium/ismail-mohamed-january-2023-headshot_medium.jpg",
    "website": "https://www.ohiohouse.gov/members/ismail-mohamed",
    "office": "77 S. High St. 10th Floor, Columbus, OH 43215"
  },
  {
    "id": "ocd-person/f2e79c7c-7e3a-496d-8f87-d43b62eb54a5",
    "name": "Kyle Koehler",
    "firstName": "Kyle",
    "lastName": "Koehler",
    "chamber": "upper",
    "district": "10",
    "party": "Republican",
    "email": "sd10@ohiosenate.gov",
    "phone": "614-466-3780",
    "photoUrl": "https://www.legislature.ohio.gov/Assets/HouseMembers/Headshots/Medium/2823.jpg",
    "website": "https://ohiohouse.gov/j-kyle-koehler",
    "office": "Room 35, Statehouse, 1 Capitol Square Ground Floor, Columbus, OH 43215"
  },
  {
    "id": "ocd-person/9c459852-5ff7-4607-a09a-6ee2480dece1",
    "name": "Jack Daniels",
    "firstName": "Jack",
    "lastName": "Daniels",
    "chamber": "lower",
    "district": "32",
    "party": "Republican",
    "email": "rep32@ohiohouse.gov",
    "phone": "614-466-1790",
    "photoUrl": "https://s3.amazonaws.com/ballotpedia-api4/files/thumbs/200/300/JackKDaniels24.png",
    "website": "https://www.ohiohouse.gov/members/jack-k-daniels",
    "office": "77 S. High St. 11th Floor, Columbus, OH 43215"
  },
  {
    "id": "ocd-person/1a598246-01e8-44c8-beca-2c41e1bafb77",
    "name": "Jim Hoops",
    "firstName": "Jim",
    "lastName": "Hoops",
    "chamber": "lower",
    "district": "81",
    "party": "Republican",
    "email": "rep81@ohiohouse.gov",
    "phone": "614-466-3760",
    "photoUrl": "https://www.legislature.ohio.gov/assets/people/james-m-hoops/headshots/thumbnails/medium/james-m-hoops-january-2021-headshot_medium.jpg",
    "website": "https://ohiohouse.gov/james-m-hoops",
    "office": "77 S. High St. 13th Floor, Columbus, OH 43215"
  },
  {
    "id": "ocd-person/4b7cbc16-7a67-4a61-8fd5-77a857270774",
    "name": "Jamie Callender",
    "firstName": "Jamie",
    "lastName": "Callender",
    "chamber": "lower",
    "district": "57",
    "party": "Republican",
    "email": "rep57@ohiohouse.gov",
    "phone": "614-644-6074",
    "photoUrl": "https://www.legislature.ohio.gov/assets/people/jamie-callender/headshots/thumbnails/medium/jamie-callender-january-2021-headshot_medium.jpg",
    "website": "https://ohiohouse.gov/jamie-callender",
    "office": "77 S. High St. 13th Floor, Columbus, OH 43215"
  },
  {
    "id": "ocd-person/c3b1dc5e-4913-4e2f-b2a8-4db5b3faa1bd",
    "name": "Jane Timken",
    "firstName": "Jane",
    "lastName": "Timken",
    "chamber": "upper",
    "district": "29",
    "party": "Republican",
    "email": "sd29@ohiosenate.gov",
    "phone": "614-466-0626",
    "website": "https://www.ohiosenate.gov/members/jane-m-timken",
    "office": "Room 134, Statehouse, 1 Capitol Square First Floor, Columbus, OH 43215"
  },
  {
    "id": "ocd-person/fbd5ca34-d2ed-41d0-a0f8-03ee8eca8a4d",
    "name": "Jason Stephens",
    "firstName": "Jason",
    "lastName": "Stephens",
    "chamber": "lower",
    "district": "93",
    "party": "Republican",
    "email": "rep93@ohiohouse.gov",
    "phone": "614-466-1366",
    "photoUrl": "https://www.legislature.ohio.gov/assets/people/jason-stephens/headshots/thumbnails/medium/jason-stephens-november-2023-headshot_medium.jpg",
    "website": "https://ohiohouse.gov/jason-stephens",
    "office": "77 S. High St. 13th Floor, Columbus, OH 43215"
  },
  {
    "id": "ocd-person/392629a2-7bb2-47df-8128-d4cd7d858324",
    "name": "Jean Schmidt",
    "firstName": "Jean",
    "lastName": "Schmidt",
    "chamber": "lower",
    "district": "62",
    "party": "Republican",
    "email": "rep62@ohiohouse.gov",
    "phone": "614-466-8134",
    "website": "https://ohiohouse.gov/jean-schmidt",
    "office": "77 S. High St. 12th Floor, Columbus, OH 43215"
  },
  {
    "id": "ocd-person/60fdc824-a8ab-44fa-80ca-053d8698218e",
    "name": "Jeff LaRe",
    "firstName": "Jeff",
    "lastName": "LaRe",
    "chamber": "lower",
    "district": "73",
    "party": "Republican",
    "email": "rep73@ohiohouse.gov",
    "phone": "614-466-8100",
    "photoUrl": "https://www.legislature.ohio.gov/assets/people/jeff-lare/headshots/thumbnails/medium/jeff-lare-january-2021-headshot_medium.jpg",
    "website": "https://ohiohouse.gov/jeff-lare",
    "office": "77 S. High St. 13th Floor, Columbus, OH 43215"
  },
  {
    "id": "ocd-person/4817cf28-df1f-4ccc-bc09-25809222e530",
    "name": "Jennifer Gross",
    "firstName": "Jennifer",
    "lastName": "Gross",
    "chamber": "lower",
    "district": "45",
    "party": "Republican",
    "email": "rep45@ohiohouse.gov",
    "phone": "614-466-8550",
    "photoUrl": "https://www.legislature.ohio.gov/assets/people/jennifer-gross/headshots/thumbnails/medium/jennifer-gross-july-2023-headshot_medium.jpg",
    "website": "https://ohiohouse.gov/jennifer-gross",
    "office": "77 S. High St. 13th Floor, Columbus, OH 43215"
  },
  {
    "id": "ocd-person/b27fdceb-e9c1-46b8-9fc2-323c3f6f784c",
    "name": "Jerry Cirino",
    "firstName": "Jerry",
    "lastName": "Cirino",
    "chamber": "upper",
    "district": "18",
    "party": "Republican",
    "email": "sd18@ohiosenate.gov",
    "phone": "614-644-7718",
    "photoUrl": "https://www.legislature.ohio.gov/assets/people/jerry-c-cirino/headshots/thumbnails/medium/jerry-c-cirino-march-2023-headshot_medium.jpg",
    "website": "https://ohiosenate.gov/members/jerry-c-cirino",
    "office": "Room 127, Statehouse, 1 Capitol Square First Floor, Columbus, OH 43215"
  },
  {
    "id": "ocd-person/ba95511f-3692-426c-bf85-c41ff737eeec",
    "name": "Jim Thomas",
    "firstName": "Jim",
    "lastName": "Thomas",
    "chamber": "lower",
    "district": "49",
    "party": "Republican",
    "email": "rep49@ohiohouse.gov",
    "phone": "614-466-8030",
    "photoUrl": "https://www.legislature.ohio.gov/assets/people/jim-thomas/headshots/thumbnails/medium/jim-thomas-november-2023-headshot_medium.jpg",
    "website": "https://www.ohiohouse.gov/members/jim-thomas",
    "office": "77 S. High St. 11th Floor, Columbus, OH 43215"
  },
  {
    "id": "ocd-person/f1715f7b-6a29-4dd2-a34f-b94c87088890",
    "name": "Jodi Salvo",
    "firstName": "Jodi",
    "lastName": "Salvo",
    "chamber": "lower",
    "district": "51",
    "party": "Republican",
    "email": "rep51@ohiohouse.gov",
    "phone": "614-466-8035",
    "photoUrl": "https://s3.amazonaws.com/ballotpedia-api4/files/thumbs/200/300/JodiSalvo.jpg",
    "website": "https://ohiohouse.gov/members/jodi-salvo",
    "office": "77 S. High St. 11th Floor, Columbus, OH 43215"
  },
  {
    "id": "ocd-person/9d7cc971-9ed9-4918-b93f-39d41d35e565",
    "name": "Johnathan Newman",
    "firstName": "Johnathan",
    "lastName": "Newman",
    "chamber": "lower",
    "district": "80",
    "party": "Republican",
    "email": "rep80@ohiohouse.gov",
    "phone": "614-466-8114",
    "photoUrl": "https://s3.amazonaws.com/ballotpedia-api4/files/thumbs/200/300/JohnathanNewman2024.jpeg",
    "website": "https://ohiohouse.gov/members/johnathan-newman",
    "office": "77 S. High St. 11th Floor, Columbus, OH 43215"
  },
  {
    "id": "ocd-person/9b5a9ff9-b35a-49aa-aa64-5d2bab574843",
    "name": "Joe Miller",
    "firstName": "Joe",
    "lastName": "Miller",
    "chamber": "lower",
    "district": "53",
    "party": "Democratic",
    "email": "rep53@ohiohouse.gov",
    "phone": "614-466-5141",
    "photoUrl": "https://www.legislature.ohio.gov/assets/people/joseph-a-miller-iii/headshots/thumbnails/medium/joseph-a-miller-iii-january-2021-headshot_medium.jpg",
    "website": "https://ohiohouse.gov/joseph-a-miller-iii",
    "office": "77 S. High St. 10th Floor, Columbus, OH 43215"
  },
  {
    "id": "ocd-person/1e52d1da-3e5c-442e-a460-d63b62709edf",
    "name": "Josh Williams",
    "firstName": "Josh",
    "lastName": "Williams",
    "chamber": "lower",
    "district": "44",
    "party": "Republican",
    "email": "rep44@ohiohouse.gov",
    "phone": "614-466-1418",
    "photoUrl": "https://www.legislature.ohio.gov/assets/people/josh-williams/headshots/thumbnails/medium/josh-williams-january-2023-headshot_medium.jpg",
    "website": "https://www.ohiohouse.gov/members/josh-williams",
    "office": "77 S. High St. 11th Floor, Columbus, OH 43215"
  },
  {
    "id": "ocd-person/ede2c8b0-9c35-4ebf-9a4a-4349fe4cc224",
    "name": "Juanita Brent",
    "firstName": "Juanita",
    "lastName": "Brent",
    "chamber": "lower",
    "district": "18",
    "party": "Democratic",
    "email": "rep18@ohiohouse.gov",
    "phone": "614-466-1408",
    "photoUrl": "https://www.legislature.ohio.gov/assets/people/juanita-o-brent/headshots/thumbnails/medium/juanita-o-brent-january-2019-headshot_medium.jpg",
    "website": "https://ohiohouse.gov/juanita-o-brent",
    "office": "77 S. High St. 10th Floor, Columbus, OH 43215"
  },
  {
    "id": "ocd-person/9892fcd7-9432-425f-85a6-7599fbe3177d",
    "name": "Justin Pizzulli",
    "firstName": "Justin",
    "lastName": "Pizzulli",
    "chamber": "lower",
    "district": "90",
    "party": "Republican",
    "email": "rep90@ohiohouse.gov",
    "phone": "614-466-2124",
    "photoUrl": "https://www.legislature.ohio.gov/assets/people/justin-pizzulli/headshots/thumbnails/medium/justin-pizzulli-july-2023-headshot_medium.jpg",
    "website": "https://ohiohouse.gov/members/justin-pizzulli",
    "office": "77 S. High St. 13th Floor, Columbus, OH 43215"
  },
  {
    "id": "ocd-person/a13af74a-5ade-4769-8a76-db942fe71002",
    "name": "Karen Brownlee",
    "firstName": "Karen",
    "lastName": "Brownlee",
    "chamber": "lower",
    "district": "28",
    "party": "Democratic",
    "email": "rep28@ohiohouse.gov",
    "phone": "614-466-8120",
    "photoUrl": "https://www.gongwer-oh.com/public/KarenBrownlee_Cropped.png",
    "website": "https://ohiohouse.gov/members/karen-brownlee",
    "office": "77 S. High St. 10th Floor, Columbus, OH 43215"
  },
  {
    "id": "ocd-person/97821235-4116-44d1-b58b-acf822bbdc58",
    "name": "Kellie Deeter",
    "firstName": "Kellie",
    "lastName": "Deeter",
    "chamber": "lower",
    "district": "54",
    "party": "Republican",
    "email": "rep54@ohiohouse.gov",
    "phone": "614-466-9628",
    "photoUrl": "https://s3.amazonaws.com/ballotpedia-api4/files/thumbs/200/300/Kellie_Deeter_20240829_073240.jpg",
    "website": "https://ohiohouse.gov/members/kellie-deeter",
    "office": "77 S. High St. 13th Floor, Columbus, OH 43215"
  },
  {
    "id": "ocd-person/d9c3dfce-8b7f-402f-9dec-5179e38b528f",
    "name": "Kent Smith",
    "firstName": "Kent",
    "lastName": "Smith",
    "chamber": "upper",
    "district": "21",
    "party": "Democratic",
    "email": "sd21@ohiosenate.gov",
    "phone": "614-466-4857",
    "photoUrl": "https://www.legislature.ohio.gov/assets/people/kent-smith/headshots/thumbnails/medium/kent-smith-may-2023-headshot_medium.jpg",
    "website": "https://ohiohouse.gov/kent-smith",
    "office": "Room 223, Statehouse, 1 Capitol Square Second Floor, Columbus, OH 43215"
  },
  {
    "id": "ocd-person/cefb7a31-f46c-4145-9f38-901be3b70e60",
    "name": "Kevin Miller",
    "firstName": "Kevin",
    "lastName": "Miller",
    "chamber": "lower",
    "district": "69",
    "party": "Republican",
    "email": "rep69@ohiohouse.gov",
    "phone": "614-466-2500",
    "photoUrl": "https://www.legislature.ohio.gov/assets/people/kevin-d-miller/headshots/thumbnails/medium/kevin-d-miller-january-2021-headshot_medium.jpg",
    "website": "https://ohiohouse.gov/kevin-d-miller",
    "office": "77 S. High St. 13th Floor, Columbus, OH 43215"
  },
  {
    "id": "ocd-person/94df9e98-c52e-466a-ba6b-29cc21ee02ea",
    "name": "Kevin Ritter",
    "firstName": "Kevin",
    "lastName": "Ritter",
    "chamber": "lower",
    "district": "94",
    "party": "Republican",
    "email": "rep94@ohiohouse.gov",
    "phone": "614-466-2158",
    "photoUrl": "https://s3.amazonaws.com/ballotpedia-api4/files/thumbs/200/300/Kevin_KevinRitter_20240808_092548.jpg",
    "website": "https://ohiohouse.gov/members/kevin-ritter",
    "office": "77 S. High St. 11th Floor, Columbus, OH 43215"
  },
  {
    "id": "ocd-person/936e5d50-e145-494b-a397-f56570530816",
    "name": "Kristina Roegner",
    "firstName": "Kristina",
    "lastName": "Roegner",
    "chamber": "upper",
    "district": "27",
    "party": "Republican",
    "email": "sd27@ohiosenate.gov",
    "phone": "614-466-4823",
    "photoUrl": "https://www.legislature.ohio.gov/assets/people/kristina-d-roegner/headshots/thumbnails/medium/kristina-d-roegner-may-2023-headshot_medium.jpg",
    "website": "https://www.ohiosenate.gov/members/kristina-d-roegner",
    "office": "Room 142, Statehouse, 1 Capitol Square First Floor, Columbus, OH 43215"
  },
  {
    "id": "ocd-person/b2c76bf8-569f-4e80-bd3d-fa8273a8356c",
    "name": "Latyna Humphrey",
    "firstName": "Latyna",
    "lastName": "Humphrey",
    "chamber": "lower",
    "district": "2",
    "party": "Democratic",
    "email": "rep02@ohiohouse.gov",
    "phone": "614-466-8010",
    "photoUrl": "https://www.legislature.ohio.gov/assets/people/latyna-m-humphrey/headshots/thumbnails/medium/latyna-m-humphrey-january-2023-headshot_medium.jpg",
    "website": "https://ohiohouse.gov/latyna-m-humphrey",
    "office": "77 S. High St. 10th Floor, Columbus, OH 43215"
  },
  {
    "id": "ocd-person/19cbe255-2cdb-47c4-b70a-693b6bf6665b",
    "name": "Lauren McNally",
    "firstName": "Lauren",
    "lastName": "McNally",
    "chamber": "lower",
    "district": "58",
    "party": "Democratic",
    "email": "rep58@ohiohouse.gov",
    "phone": "614-466-9435",
    "photoUrl": "https://www.legislature.ohio.gov/assets/people/lauren-mcnally/headshots/thumbnails/medium/lauren-mcnally-february-2023-headshot_medium.jpg",
    "website": "https://www.ohiohouse.gov/members/lauren-mcnally",
    "office": "77 S. High St. 10th Floor, Columbus, OH 43215"
  },
  {
    "id": "ocd-person/1dcb1bfa-861d-4d16-8d7d-02364e1b4def",
    "name": "Levi Dean",
    "firstName": "Levi",
    "lastName": "Dean",
    "chamber": "lower",
    "district": "71",
    "party": "Republican",
    "email": "rep71@ohiohouse.gov",
    "phone": "614-466-1470",
    "photoUrl": "https://assets.civicengine.com/uploads/candidate/headshot/678132/678132.jpg",
    "website": "https://ohiohouse.gov/members/levi-dean",
    "office": "77 S. High St. 11th Floor, Columbus, OH 43215"
  },
  {
    "id": "ocd-person/5a9b2a16-6827-4e00-961a-f3de39538749",
    "name": "Bill Blessing",
    "firstName": "Bill",
    "lastName": "Blessing",
    "chamber": "upper",
    "district": "8",
    "party": "Republican",
    "email": "sd08@ohiosenate.gov",
    "phone": "614-466-8068",
    "photoUrl": "https://www.legislature.ohio.gov/assets/people/louis-w-blessing-iii/headshots/thumbnails/medium/louis-w-blessing-iii-march-2023-headshot_medium.jpg",
    "website": "https://www.ohiosenate.gov/members/louis-w-blessing-iii",
    "office": "Room 143, Statehouse, 1 Capitol Square First Floor, Columbus, OH 43215"
  },
  {
    "id": "ocd-person/e4f9416c-1043-4737-899e-31410e94af1d",
    "name": "Marilyn John",
    "firstName": "Marilyn",
    "lastName": "John",
    "chamber": "lower",
    "district": "76",
    "party": "Republican",
    "email": "rep76@ohiohouse.gov",
    "phone": "614-466-5802",
    "photoUrl": "https://www.legislature.ohio.gov/assets/people/marilyn-s-john/headshots/thumbnails/medium/marilyn-s-john-january-2023-headshot_medium.jpg",
    "website": "https://ohiohouse.gov/marilyn-s-john",
    "office": "77 S. High St. 14th Floor, Columbus, OH 43215"
  },
  {
    "id": "ocd-person/292d1329-8a45-402b-8d6e-8f3b4726187a",
    "name": "Mark Hiner",
    "firstName": "Mark",
    "lastName": "Hiner",
    "chamber": "lower",
    "district": "98",
    "party": "Republican",
    "email": "rep98@ohiohouse.gov",
    "phone": "614-466-2994",
    "photoUrl": "https://s3.amazonaws.com/ballotpedia-api4/files/thumbs/200/300/Mark_Hiner.jpg",
    "website": "https://ohiohouse.gov/members/mark-hiner",
    "office": "77 S. High St. 13th Floor, Columbus, OH 43215"
  },
  {
    "id": "ocd-person/4af0e8db-ad18-424f-abfa-ce31e37c0b7d",
    "name": "Mark Johnson",
    "firstName": "Mark",
    "lastName": "Johnson",
    "chamber": "lower",
    "district": "92",
    "party": "Republican",
    "email": "rep92@ohiohouse.gov",
    "phone": "614-644-7928",
    "photoUrl": "https://www.legislature.ohio.gov/assets/people/mark-johnson/headshots/thumbnails/medium/mark-johnson-january-2021-headshot_medium.jpg",
    "website": "https://ohiohouse.gov/mark-johnson",
    "office": "77 S. High St. 12th Floor, Columbus, OH 43215"
  },
  {
    "id": "ocd-person/2ae62dc8-e902-4a8e-99b7-182477c50bc3",
    "name": "Mark Romanchuk",
    "firstName": "Mark",
    "lastName": "Romanchuk",
    "chamber": "upper",
    "district": "22",
    "party": "Republican",
    "email": "sd22@ohiosenate.gov",
    "phone": "614-466-7505",
    "photoUrl": "https://www.legislature.ohio.gov/assets/people/mark-romanchuk/headshots/thumbnails/medium/mark-romanchuk-may-2023-headshot_medium.jpg",
    "website": "https://www.ohiosenate.gov/members/mark-romanchuk",
    "office": "Room 132, Statehouse, 1 Capitol Square First Floor, Columbus, OH 43215"
  },
  {
    "id": "ocd-person/8750be20-9a0c-41e4-bb32-4061c787a7e2",
    "name": "Mark Sigrist",
    "firstName": "Mark",
    "lastName": "Sigrist",
    "chamber": "lower",
    "district": "10",
    "party": "Democratic",
    "email": "rep10@ohiohouse.gov",
    "phone": "614-466-9690",
    "photoUrl": "https://images.squarespace-cdn.com/content/v1/662d9bb55b29343555b12d33/fdca756a-8e4a-41ea-aed9-0ec72d720e82/cropped.jpg?format=750w",
    "website": "https://ohiohouse.gov/members/mark-sigrist",
    "office": "77 S. High St. 10th Floor, Columbus, OH 43215"
  },
  {
    "id": "ocd-person/23d51717-c6eb-4a2c-bd55-038c72593a61",
    "name": "Matt Huffman",
    "firstName": "Matt",
    "lastName": "Huffman",
    "chamber": "lower",
    "district": "78",
    "party": "Republican",
    "email": "rep78@ohiohouse.gov",
    "phone": "614-466-6344",
    "photoUrl": "https://www.legislature.ohio.gov/assets/people/matt-huffman/headshots/thumbnails/medium/matt-huffman-may-2023-headshot_medium.jpg",
    "website": "https://ohiohouse.gov/members/matt-huffman",
    "office": "77 S. High St. 14th Floor, Columbus, OH 43215"
  },
  {
    "id": "ocd-person/7ab0cf86-d569-4a6e-8677-8cd7721a9475",
    "name": "Matt Kishman",
    "firstName": "Matt",
    "lastName": "Kishman",
    "chamber": "lower",
    "district": "50",
    "party": "Republican",
    "email": "rep50@ohiohouse.gov",
    "phone": "614-466-9078",
    "photoUrl": "https://images.squarespace-cdn.com/content/v1/65a09d4d50790252eca6f810/be978e73-e9f1-4978-9bcf-9553f9a6d410/Kishman+Matthew_2270.jpg?format=500w",
    "website": "https://ohiohouse.gov/members/matthew-kishman",
    "office": "77 S. High St. 11th Floor, Columbus, OH 43215"
  },
  {
    "id": "ocd-person/fb957ddc-f41c-400d-ae32-47f7e729555b",
    "name": "Melanie Miller",
    "firstName": "Melanie",
    "lastName": "Miller",
    "chamber": "lower",
    "district": "67",
    "party": "Republican",
    "email": "rep67@ohiohouse.gov",
    "phone": "614-466-0961",
    "photoUrl": "https://www.legislature.ohio.gov/assets/people/melanie-miller/headshots/thumbnails/medium/melanie-miller-january-2023-headshot_medium.jpg",
    "website": "https://www.ohiohouse.gov/members/melanie-miller",
    "office": "77 S. High St. 12th Floor, Columbus, OH 43215"
  },
  {
    "id": "ocd-person/75257af6-5d83-4d3b-b127-744aaa377c9f",
    "name": "Meredith Craig",
    "firstName": "Meredith",
    "lastName": "Craig",
    "chamber": "lower",
    "district": "77",
    "party": "Republican",
    "email": "rep77@ohiohouse.gov",
    "phone": "614-466-1474",
    "photoUrl": "https://www.meredithcraigforohio.com/dejilah/sites/522/2024/08/craig-new-photo.png",
    "website": "https://ohiohouse.gov/members/meredith-craig",
    "office": "77 S. High St. 11th Floor, Columbus, OH 43215"
  },
  {
    "id": "ocd-person/4b1e7c00-c159-407e-83d8-2eb24ba175db",
    "name": "Meredith Lawson‐Rowe",
    "firstName": "Meredith",
    "lastName": "Lawson‐Rowe",
    "chamber": "lower",
    "district": "5",
    "party": "Democratic",
    "email": "rep05@ohiohouse.gov",
    "phone": "614-644-6002",
    "photoUrl": "https://thenewamericansmag.com/wp-content/uploads/2024/03/Meredith-Lawson-Rowe.jpg",
    "website": "https://ohiohouse.gov/members/meredith-r-lawson-rowe",
    "office": "77 S. High St. 10th Floor, Columbus, OH 43215"
  },
  {
    "id": "ocd-person/100ae6b0-0c5d-4b97-9ac5-8ccb42b9168b",
    "name": "Michele Grim",
    "firstName": "Michele",
    "lastName": "Grim",
    "chamber": "lower",
    "district": "43",
    "party": "Democratic",
    "email": "rep43@ohiohouse.gov",
    "phone": "614-644-6017",
    "photoUrl": "https://www.legislature.ohio.gov/assets/people/michele-grim/headshots/thumbnails/medium/michele-grim-november-2023-headshot_medium.jpg",
    "website": "https://www.ohiohouse.gov/members/michele-grim",
    "office": "77 S. High St. 14th Floor, Columbus, OH 43215"
  },
  {
    "id": "ocd-person/79af20c0-6eb6-44a2-ba79-9c7e5e10ea04",
    "name": "Michele Reynolds",
    "firstName": "Michele",
    "lastName": "Reynolds",
    "chamber": "upper",
    "district": "3",
    "party": "Republican",
    "email": "reynolds@ohiosenate.gov",
    "phone": "614-466-8064",
    "photoUrl": "https://www.legislature.ohio.gov/assets/people/michele-reynolds/headshots/thumbnails/medium/michele-reynolds-may-2023-headshot_medium.jpg",
    "website": "https://www.ohiosenate.gov/members/michele-reynolds",
    "office": "Room 128, Statehouse, 1 Capitol Square First Floor, Columbus, OH 43215"
  },
  {
    "id": "ocd-person/d06c06f8-2f63-4a29-8388-ed0747b97f48",
    "name": "Michelle Teska",
    "firstName": "Michelle",
    "lastName": "Teska",
    "chamber": "lower",
    "district": "55",
    "party": "Republican",
    "email": "rep55@ohiohouse.gov",
    "phone": "614-644-6023",
    "photoUrl": "https://static.wixstatic.com/media/57b3a5_db008a611c184fbeb2cf20bb55a41080~mv2.jpg/v1/fill/w_689,h_812,al_c,q_85,usm_0.66_1.00_0.01,enc_avif,quality_auto/Michelle%20(15%20of%2024)%20(1)_edited.jpg",
    "website": "https://ohiohouse.gov/members/michelle-teska",
    "office": "77 S. High St. 11th Floor, Columbus, OH 43215"
  },
  {
    "id": "ocd-person/cc85c295-299f-4de7-bb56-1de3a451951e",
    "name": "Mike Dovilla",
    "firstName": "Mike",
    "lastName": "Dovilla",
    "chamber": "lower",
    "district": "17",
    "party": "Republican",
    "email": "rep17@ohiohouse.gov",
    "phone": "614-466-4895",
    "photoUrl": "http://www.ohiohouse.gov/Assets/Headshots/Small/7.jpg",
    "website": "https://www.ohiohouse.gov/members/michael-d-dovilla",
    "office": "77 S. High St. 13th Floor, Columbus, OH 43215"
  },
  {
    "id": "ocd-person/72bb7360-10c1-42d9-8781-32ddf8fef5fd",
    "name": "Mike Odioso",
    "firstName": "Mike",
    "lastName": "Odioso",
    "chamber": "lower",
    "district": "30",
    "party": "Republican",
    "email": "rep30@ohiohouse.gov",
    "phone": "614-466-8258",
    "photoUrl": "https://s3.amazonaws.com/ballotpedia-api4/files/thumbs/200/300/MikeOdioso2024.jpg",
    "website": "https://ohiohouse.gov/members/mike-odioso",
    "office": "77 S. High St. 13th Floor, Columbus, OH 43215"
  },
  {
    "id": "ocd-person/062b9622-c2fa-4af2-bbea-704f0450dd47",
    "name": "Monica Blasdel",
    "firstName": "Monica",
    "lastName": "Blasdel",
    "chamber": "lower",
    "district": "79",
    "party": "Republican",
    "email": "rep79@ohiohouse.gov",
    "phone": "614-466-8022",
    "photoUrl": "https://www.legislature.ohio.gov/assets/people/monica-robb-blasdel/headshots/thumbnails/medium/monica-robb-blasdel-january-2023-headshot_medium.jpg",
    "website": "https://www.ohiohouse.gov/members/monica-robb-blasdel",
    "office": "77 S. High St. 11th Floor, Columbus, OH 43215"
  },
  {
    "id": "ocd-person/538fefb8-d8ae-48f5-bb07-4161e2ccac55",
    "name": "Munira Abdullahi",
    "firstName": "Munira",
    "lastName": "Abdullahi",
    "chamber": "lower",
    "district": "9",
    "party": "Democratic",
    "email": "rep09@ohiohouse.gov",
    "phone": "614-466-2473",
    "photoUrl": "https://www.legislature.ohio.gov/assets/people/munira-abdullahi/headshots/thumbnails/medium/munira-yasin-abdullahi-february-2023-headshot_medium.jpg",
    "website": "https://www.ohiohouse.gov/members/munira-abdullahi",
    "office": "77 S. High St. 10th Floor, Columbus, OH 43215"
  },
  {
    "id": "ocd-person/d3508136-3927-461f-a2f0-a85665845ab1",
    "name": "Nathan Manning",
    "firstName": "Nathan",
    "lastName": "Manning",
    "chamber": "upper",
    "district": "13",
    "party": "Republican",
    "email": "sd13@ohiosenate.gov",
    "phone": "614-644-7613",
    "photoUrl": "https://www.legislature.ohio.gov/assets/people/nathan-h-manning/headshots/thumbnails/medium/nathan-h-manning-may-2023-headshot_medium.jpg",
    "website": "https://www.ohiosenate.gov/members/nathan-h-manning",
    "office": "Room 39, Statehouse, 1 Capitol Square Ground Floor, Columbus, OH 43215"
  },
  {
    "id": "ocd-person/64305698-f25c-486e-b57f-00298cfbe15d",
    "name": "Nick Santucci",
    "firstName": "Nick",
    "lastName": "Santucci",
    "chamber": "lower",
    "district": "64",
    "party": "Republican",
    "email": "rep64@ohiohouse.gov",
    "phone": "614-466-5441",
    "photoUrl": "https://www.legislature.ohio.gov/assets/people/nick-santucci/headshots/thumbnails/medium/nick-santucci-january-2023-headshot_medium.jpg",
    "website": "https://www.ohiohouse.gov/members/nick-santucci",
    "office": "77 S. High St. 13th Floor, Columbus, OH 43215"
  },
  {
    "id": "ocd-person/df5c391c-65e8-4d61-a9b9-0249ff6eddb7",
    "name": "Nickie Antonio",
    "firstName": "Nickie",
    "lastName": "Antonio",
    "chamber": "upper",
    "district": "23",
    "party": "Democratic",
    "email": "sd23@ohiosenate.gov",
    "phone": "614-466-5123",
    "photoUrl": "https://www.legislature.ohio.gov/assets/people/nickie-j-antonio/headshots/thumbnails/medium/nickie-j-antonio-may-2023-headshot_medium.jpg",
    "website": "https://www.ohiosenate.gov/members/nickie-j-antonio",
    "office": "Room SH-303, Statehouse, 1 Capitol Square Third Floor, Columbus, OH 43215"
  },
  {
    "id": "ocd-person/3329274c-22b6-4b0a-b12a-e64c5733bef9",
    "name": "Paula Hicks-Hudson",
    "firstName": "Paula",
    "lastName": "Hicks-Hudson",
    "chamber": "upper",
    "district": "11",
    "party": "Democratic",
    "email": "sd11@ohiosenate.gov",
    "phone": "614-466-5204",
    "photoUrl": "https://www.legislature.ohio.gov/assets/people/paula-hicks-hudson/headshots/thumbnails/medium/paula-hicks-hudson-may-2023-headshot_medium.jpg",
    "website": "https://ohiohouse.gov/paula-hicks-hudson",
    "office": "Room 57, Statehouse, 1 Capitol Square Ground Floor, Columbus, OH 43215"
  },
  {
    "id": "ocd-person/1e218942-95f6-43fe-b935-b19ab70fd5fc",
    "name": "Phil Plummer",
    "firstName": "Phil",
    "lastName": "Plummer",
    "chamber": "lower",
    "district": "39",
    "party": "Republican",
    "email": "rep39@ohiohouse.gov",
    "phone": "614-644-8051",
    "photoUrl": "https://www.legislature.ohio.gov/assets/people/phil-plummer/headshots/thumbnails/medium/phil-plummer-january-2021-headshot_medium.jpg",
    "website": "https://ohiohouse.gov/phil-plummer",
    "office": "77 S. High St. 14th Floor, Columbus, OH 43215"
  },
  {
    "id": "ocd-person/78d5adbb-ec6a-4212-9cc7-335f5d9ded8c",
    "name": "Phil Robinson",
    "firstName": "Phil",
    "lastName": "Robinson",
    "chamber": "lower",
    "district": "19",
    "party": "Democratic",
    "email": "rep19@ohiohouse.gov",
    "phone": "614-644-6041",
    "photoUrl": "https://www.legislature.ohio.gov/assets/people/phillip-m-robinson-jr/headshots/thumbnails/medium/phillip-m-robinson-jr-january-2019-headshot_medium.jpg",
    "website": "https://ohiohouse.gov/phillip-m-robinson-jr",
    "office": "77 S. High St. 10th Floor, Columbus, OH 43215"
  },
  {
    "id": "ocd-person/36f320a8-be34-43c2-ac73-ee87fbce6b0c",
    "name": "Rachel Baker",
    "firstName": "Rachel",
    "lastName": "Baker",
    "chamber": "lower",
    "district": "27",
    "party": "Democratic",
    "email": "rep27@ohiohouse.gov",
    "phone": "614-644-6886",
    "photoUrl": "https://www.legislature.ohio.gov/assets/people/rachel-b-baker/headshots/thumbnails/medium/rachel-b-baker-january-2023-headshot_medium.jpg",
    "website": "https://www.ohiohouse.gov/members/rachel-b-baker",
    "office": "77 S. High St. 10th Floor, Columbus, OH 43215"
  },
  {
    "id": "ocd-person/d6ca7e4f-dcf2-4aad-a919-a2740bae649a",
    "name": "Riordan McClain",
    "firstName": "Riordan",
    "lastName": "McClain",
    "chamber": "lower",
    "district": "87",
    "party": "Republican",
    "email": "rep87@ohiohouse.gov",
    "phone": "614-644-6265",
    "photoUrl": "https://www.legislature.ohio.gov/assets/people/riordan-t-mcclain/headshots/thumbnails/medium/riordan-t-mcclain-january-2021-headshot_medium.jpg",
    "website": "https://ohiohouse.gov/members/riordan-t-mcclain",
    "office": "77 S. High St. 14th Floor, Columbus, OH 43215"
  },
  {
    "id": "ocd-person/e0d52f86-e997-4299-9e50-972a2c208c20",
    "name": "Rob McColley",
    "firstName": "Rob",
    "lastName": "McColley",
    "chamber": "upper",
    "district": "1",
    "party": "Republican",
    "email": "sd01@ohiosenate.gov",
    "phone": "614-466-8150",
    "photoUrl": "https://www.legislature.ohio.gov/assets/people/rob-mccolley/headshots/thumbnails/medium/rob-mccolley-may-2023-headshot_medium.jpg",
    "website": "https://www.ohiosenate.gov/members/rob-mccolley",
    "office": "Room 201, Statehouse, 1 Capitol Square Second Floor, Columbus, OH 43215"
  },
  {
    "id": "ocd-person/c34a852a-71fc-4b21-a594-bc4a75b799c8",
    "name": "Rodney Creech",
    "firstName": "Rodney",
    "lastName": "Creech",
    "chamber": "lower",
    "district": "40",
    "party": "Republican",
    "email": "rep40@ohiohouse.gov",
    "phone": "614-466-2960",
    "photoUrl": "https://www.legislature.ohio.gov/assets/people/rodney-creech/headshots/thumbnails/medium/rodney-creech-january-2021-headshot_medium.jpg",
    "website": "https://ohiohouse.gov/members/rodney-creech",
    "office": "77 S. High St. 12th Floor, Columbus, OH 43215"
  },
  {
    "id": "ocd-person/52608475-9678-45ce-823a-74f9c931682c",
    "name": "Ron Ferguson",
    "firstName": "Ron",
    "lastName": "Ferguson",
    "chamber": "lower",
    "district": "96",
    "party": "Republican",
    "email": "rep96@ohiohouse.gov",
    "phone": "614-466-3735",
    "photoUrl": "https://www.legislature.ohio.gov/assets/people/ron-ferguson/headshots/thumbnails/medium/ron-ferguson-january-2021-headshot_medium.jpg",
    "website": "https://ohiohouse.gov/members/ron-ferguson",
    "office": "77 S. High St. 13th Floor, Columbus, OH 43215"
  },
  {
    "id": "ocd-person/73e72147-0d40-4478-bbf6-3419f0e00b46",
    "name": "Roy Klopfenstein",
    "firstName": "Roy",
    "lastName": "Klopfenstein",
    "chamber": "lower",
    "district": "82",
    "party": "Republican",
    "email": "rep82@ohiohouse.gov",
    "phone": "614-644-5091",
    "photoUrl": "https://www.legislature.ohio.gov/assets/people/roy-klopfenstein/headshots/thumbnails/medium/roy-klopfenstein-january-2023-headshot_medium.jpg",
    "website": "https://www.ohiohouse.gov/members/roy-klopfenstein",
    "office": "77 S. High St. 11th Floor, Columbus, OH 43215"
  },
  {
    "id": "ocd-person/d665e333-f7e3-43e2-b440-17920f62c60b",
    "name": "Sandy O'Brien",
    "firstName": "Sandy",
    "lastName": "O'Brien",
    "chamber": "upper",
    "district": "32",
    "party": "Republican",
    "email": "sd32@ohiosenate.gov",
    "phone": "614-466-7182",
    "photoUrl": "https://www.legislature.ohio.gov/assets/people/sandra-obrien/headshots/thumbnails/medium/sandra-obrien-may-2023-headshot_medium.jpg",
    "website": "https://www.ohiosenate.gov/members/sandra-obrien",
    "office": "Room 125, Statehouse, 1 Capitol Square First Floor, Columbus, OH 43215"
  },
  {
    "id": "ocd-person/5b3a7d10-e745-4985-ade9-d7fff6ae6af4",
    "name": "Sarah Fowler Arthur",
    "firstName": "Sarah",
    "lastName": "Fowler Arthur",
    "chamber": "lower",
    "district": "99",
    "party": "Republican",
    "email": "rep99@ohiohouse.gov",
    "phone": "614-466-1405",
    "photoUrl": "https://www.legislature.ohio.gov/assets/people/sarah-fowler-arthur/headshots/thumbnails/medium/sarah-fowler-arthur-february-2023-headshot_medium.jpg",
    "website": "https://ohiohouse.gov/members/sarah-fowler-arthur",
    "office": "77 S. High St. 12th Floor, Columbus, OH 43215"
  },
  {
    "id": "ocd-person/52424e91-a002-4908-a205-4ea27cfe68da",
    "name": "Scott Oelslager",
    "firstName": "Scott",
    "lastName": "Oelslager",
    "chamber": "lower",
    "district": "48",
    "party": "Republican",
    "email": "rep48@ohiohouse.gov",
    "phone": "614-752-2438",
    "photoUrl": "https://www.legislature.ohio.gov/assets/people/scott-oelslager/headshots/thumbnails/medium/scott-oelslager-february-2023-headshot_medium.jpg",
    "website": "https://ohiohouse.gov/scott-oelslager",
    "office": "77 S. High St. 13th Floor, Columbus, OH 43215"
  },
  {
    "id": "ocd-person/993f089c-60bf-418d-9704-fa92e4f01c71",
    "name": "Sean Brennan",
    "firstName": "Sean",
    "lastName": "Brennan",
    "chamber": "lower",
    "district": "14",
    "party": "Democratic",
    "email": "rep14@ohiohouse.gov",
    "phone": "614-466-3485",
    "photoUrl": "https://www.legislature.ohio.gov/assets/people/sean-p-brennan/headshots/thumbnails/medium/sean-p-brennan-january-2023-headshot_medium.jpg",
    "website": "https://www.ohiohouse.gov/members/sean-p-brennan",
    "office": "77 S. High St. 10th Floor, Columbus, OH 43215"
  },
  {
    "id": "ocd-person/bb1ae016-cdfe-48aa-8bc5-9e3636e430f3",
    "name": "Shane Wilkin",
    "firstName": "Shane",
    "lastName": "Wilkin",
    "chamber": "upper",
    "district": "17",
    "party": "Republican",
    "email": "sd17@ohiosenate.gov",
    "phone": "614-466-8156",
    "photoUrl": "https://www.legislature.ohio.gov/assets/people/shane-wilkin/headshots/thumbnails/medium/shane-wilkin-may-2023-headshot_medium.jpg",
    "website": "https://ohiohouse.gov/shane-wilkin",
    "office": "Room 221, Statehouse, 1 Capitol Square Second Floor, Columbus, OH 43215"
  },
  {
    "id": "ocd-person/352d7ee9-256c-4195-a673-17b7ee200948",
    "name": "Sharon Ray",
    "firstName": "Sharon",
    "lastName": "Ray",
    "chamber": "lower",
    "district": "66",
    "party": "Republican",
    "email": "rep66@ohiohouse.gov",
    "phone": "614-466-8140",
    "photoUrl": "https://www.legislature.ohio.gov/assets/people/sharon-a-ray/headshots/thumbnails/medium/sharon-a-ray-january-2021-headshot_medium.jpg",
    "website": "https://ohiohouse.gov/members/sharon-a-ray",
    "office": "77 S. High St. 11th Floor, Columbus, OH 43215"
  },
  {
    "id": "ocd-person/b21d9dcd-21e9-4071-936d-f89fc5d8f643",
    "name": "Steve Huffman",
    "firstName": "Steve",
    "lastName": "Huffman",
    "chamber": "upper",
    "district": "5",
    "party": "Republican",
    "email": "sd05@ohiosenate.gov",
    "phone": "614-466-6247",
    "photoUrl": "https://www.legislature.ohio.gov/assets/people/stephen-a-huffman/headshots/thumbnails/medium/stephen-a-huffman-may-2023-headshot_medium.jpg",
    "website": "https://www.ohiosenate.gov/members/stephen-a-huffman",
    "office": "Room 40, Statehouse, 1 Capitol Square Ground Floor, Columbus, OH 43215"
  },
  {
    "id": "ocd-person/854b6ce3-a4e1-46db-959a-aa286e4e8942",
    "name": "Steve Demetriou",
    "firstName": "Steve",
    "lastName": "Demetriou",
    "chamber": "lower",
    "district": "35",
    "party": "Republican",
    "email": "rep35@ohiohouse.gov",
    "phone": "614-644-5088",
    "photoUrl": "https://www.legislature.ohio.gov/assets/people/steve-demetriou/headshots/thumbnails/medium/steve-demetriou-january-2023-headshot_medium.jpg",
    "website": "https://www.ohiohouse.gov/members/steve-demetriou",
    "office": "77 S. High St. 12th Floor, Columbus, OH 43215"
  },
  {
    "id": "ocd-person/26444e7e-72b2-4838-bc24-31899c90d504",
    "name": "Steve Wilson",
    "firstName": "Steve",
    "lastName": "Wilson",
    "chamber": "upper",
    "district": "7",
    "party": "Republican",
    "email": "sd07@ohiosenate.gov",
    "phone": "614-466-9737",
    "photoUrl": "https://www.legislature.ohio.gov/assets/people/steve-wilson/headshots/thumbnails/medium/steve-wilson-may-2023-headshot_medium.jpg",
    "website": "https://www.ohiosenate.gov/members/steve-wilson",
    "office": "Room 222, Statehouse, 1 Capitol Square Second Floor, Columbus, OH 43215"
  },
  {
    "id": "ocd-person/0e44b586-f6a4-44ee-b6b7-37fa8dc2e8cd",
    "name": "Susan Manchester",
    "firstName": "Susan",
    "lastName": "Manchester",
    "chamber": "upper",
    "district": "12",
    "party": "Republican",
    "email": "sd12@ohiosenate.gov",
    "phone": "614-466-7584",
    "photoUrl": "https://www.legislature.ohio.gov/assets/people/susan-manchester/headshots/thumbnails/medium/susan-manchester-january-2023-headshot_medium.jpg",
    "website": "https://ohiohouse.gov/susan-manchester",
    "office": "Room 48, Statehouse, 1 Capitol Square Ground Floor, Columbus, OH 43215"
  },
  {
    "id": "ocd-person/a4c53220-d4a7-4591-b2d8-109516dc9401",
    "name": "Terrence Upchurch",
    "firstName": "Terrence",
    "lastName": "Upchurch",
    "chamber": "lower",
    "district": "20",
    "party": "Democratic",
    "email": "rep20@ohiohouse.gov",
    "phone": "614-466-7954",
    "photoUrl": "https://www.legislature.ohio.gov/assets/people/terrence-upchurch/headshots/thumbnails/medium/terrence-upchurch-january-2021-headshot_medium.jpg",
    "website": "https://ohiohouse.gov/terrence-upchurch",
    "office": "77 S. High St. 10th Floor, Columbus, OH 43215"
  },
  {
    "id": "ocd-person/57300c34-0e2d-4e85-bdce-c4fb8c781541",
    "name": "Terry Johnson",
    "firstName": "Terry",
    "lastName": "Johnson",
    "chamber": "upper",
    "district": "14",
    "party": "Republican",
    "email": "sd14@ohiosenate.gov",
    "phone": "614-466-8082",
    "photoUrl": "https://www.legislature.ohio.gov/assets/people/terry-johnson/headshots/thumbnails/medium/terry-johnson-may-2023-headshot_medium.jpg",
    "website": "https://www.ohiosenate.gov/members/terry-johnson",
    "office": "Room 226, Statehouse, 1 Capitol Square Second Floor, Columbus, OH 43215"
  },
  {
    "id": "ocd-person/16e469e4-8014-4ba2-8fc4-91804d6ef491",
    "name": "Tex Fischer",
    "firstName": "Tex",
    "lastName": "Fischer",
    "chamber": "lower",
    "district": "59",
    "party": "Republican",
    "email": "rep59@ohiohouse.gov",
    "phone": "614-466-6107",
    "photoUrl": "https://ogden_images.s3.amazonaws.com/www.salemnews.net/images/2024/06/27232837/Fischer-Tex.jpg",
    "website": "https://ohiohouse.gov/houseapp/members/tex-fischer",
    "office": "77 S. High St. 13th Floor, Columbus, OH 43215"
  },
  {
    "id": "ocd-person/081534e7-8952-47f0-a722-ed627fb32069",
    "name": "Thad Claggett",
    "firstName": "Thad",
    "lastName": "Claggett",
    "chamber": "lower",
    "district": "68",
    "party": "Republican",
    "email": "rep68@ohiohouse.gov",
    "phone": "614-466-1482",
    "photoUrl": "https://www.legislature.ohio.gov/assets/people/thaddeus-j-claggett/headshots/thumbnails/medium/thaddeus-j-claggett-january-2023-headshot_medium.jpg",
    "website": "https://www.ohiohouse.gov/members/thaddeus-j-claggett",
    "office": "77 S. High St. 13th Floor, Columbus, OH 43215"
  },
  {
    "id": "ocd-person/0fe32749-fe89-4f96-87d3-3d831bea2459",
    "name": "Theresa Gavarone",
    "firstName": "Theresa",
    "lastName": "Gavarone",
    "chamber": "upper",
    "district": "2",
    "party": "Republican",
    "email": "sd02@ohiosenate.gov",
    "phone": "614-466-8060",
    "photoUrl": "https://www.legislature.ohio.gov/assets/people/theresa-gavarone/headshots/thumbnails/medium/theresa-gavarone-may-2023-headshot_medium.jpg",
    "website": "https://www.ohiosenate.gov/members/theresa-gavarone",
    "office": "Room 138, Statehouse, 1 Capitol Square First Floor, Columbus, OH 43215"
  },
  {
    "id": "ocd-person/a57f6c78-ac58-4f7d-870e-0d8052984cd9",
    "name": "Tom Patton",
    "firstName": "Tom",
    "lastName": "Patton",
    "chamber": "upper",
    "district": "24",
    "party": "Republican",
    "email": "sd24@ohiosenate.gov",
    "phone": "614-466-8056",
    "photoUrl": "https://www.legislature.ohio.gov/assets/people/thomas-f-patton/headshots/thumbnails/medium/thomas-f-patton-november-2023-headshot_medium.jpg",
    "website": "https://ohiohouse.gov/thomas-f-patton",
    "office": "Room 42, Statehouse, 1 Capitol Square Ground Floor, Columbus, OH 43215"
  },
  {
    "id": "ocd-person/7948afad-ec3c-4e4c-a073-305fb8cd1b21",
    "name": "Thomas Hall",
    "firstName": "Thomas",
    "lastName": "Hall",
    "chamber": "lower",
    "district": "46",
    "party": "Republican",
    "email": "rep46@ohiohouse.gov",
    "phone": "614-644-5094",
    "photoUrl": "https://www.legislature.ohio.gov/assets/people/thomas-hall/headshots/thumbnails/medium/thomas-hall-january-2021-headshot_medium.jpg",
    "website": "https://ohiohouse.gov/members/thomas-hall",
    "office": "77 S. High St. 12th Floor, Columbus, OH 43215"
  },
  {
    "id": "ocd-person/fa5ff978-34ff-49d1-958e-4e356a8ef9d4",
    "name": "Tim Barhorst",
    "firstName": "Tim",
    "lastName": "Barhorst",
    "chamber": "lower",
    "district": "85",
    "party": "Republican",
    "email": "rep85@ohiohouse.gov",
    "phone": "614-466-1507",
    "photoUrl": "https://www.legislature.ohio.gov/assets/people/tim-barhorst/headshots/thumbnails/medium/tim-barhorst-january-2023-headshot_medium.jpg",
    "website": "https://www.ohiohouse.gov/members/tim-barhorst",
    "office": "77 S. High St. 11th Floor, Columbus, OH 43215"
  },
  {
    "id": "ocd-person/01a80305-a667-4dda-9676-1e678bddde12",
    "name": "Tim Schaffer",
    "firstName": "Tim",
    "lastName": "Schaffer",
    "chamber": "upper",
    "district": "20",
    "party": "Republican",
    "email": "sd20@ohiosenate.gov",
    "phone": "614-466-8076",
    "photoUrl": "https://www.legislature.ohio.gov/assets/people/tim-schaffer/headshots/thumbnails/medium/tim-schaffer-may-2023-headshot_medium.jpg",
    "website": "https://www.ohiosenate.gov/members/tim-schaffer",
    "office": "Room 137, Statehouse, 1 Capitol Square First Floor, Columbus, OH 43215"
  },
  {
    "id": "ocd-person/d2ecec1d-db13-4a47-836b-9e75f3a31c78",
    "name": "Tom Young",
    "firstName": "Tom",
    "lastName": "Young",
    "chamber": "lower",
    "district": "37",
    "party": "Republican",
    "email": "rep37@ohiohouse.gov",
    "phone": "614-466-6504",
    "photoUrl": "https://www.legislature.ohio.gov/assets/people/tom-young/headshots/thumbnails/medium/tom-young-january-2021-headshot_medium.jpg",
    "website": "https://ohiohouse.gov/members/tom-young",
    "office": "77 S. High St. 11th Floor, Columbus, OH 43215"
  },
  {
    "id": "ocd-person/7bcb4dfa-e4d3-46cd-b158-057b1b4b9a0a",
    "name": "Tracy Richardson",
    "firstName": "Tracy",
    "lastName": "Richardson",
    "chamber": "lower",
    "district": "86",
    "party": "Republican",
    "email": "rep86@ohiohouse.gov",
    "phone": "614-466-8147",
    "photoUrl": "https://www.legislature.ohio.gov/assets/people/tracy-m-richardson/headshots/thumbnails/medium/tracy-m-richardson-january-2023-headshot_medium.jpg",
    "website": "https://ohiohouse.gov/tracy-m-richardson",
    "office": "77 S. High St. 11th Floor, Columbus, OH 43215"
  },
  {
    "id": "ocd-person/18864718-3e48-4236-9afb-b1a61e4c52e2",
    "name": "Tristan Rader",
    "firstName": "Tristan",
    "lastName": "Rader",
    "chamber": "lower",
    "district": "13",
    "party": "Democratic",
    "email": "rep13@ohiohouse.gov",
    "phone": "614-466-5921",
    "photoUrl": "https://s3.amazonaws.com/ballotpedia-api4/files/thumbs/200/300/TristanRader2.jpg",
    "website": "https://ohiohouse.gov/members/tristan-rader",
    "office": "77 S. High St. 10th Floor, Columbus, OH 43215"
  },
  {
    "id": "ocd-person/09c752d1-59eb-4f43-b401-5092d801f4c1",
    "name": "Ty Mathews",
    "firstName": "Ty",
    "lastName": "Mathews",
    "chamber": "lower",
    "district": "83",
    "party": "Republican",
    "email": "rep83@ohiohouse.gov",
    "phone": "614-466-3819",
    "photoUrl": "https://s3.amazonaws.com/ballotpedia-api4/files/thumbs/200/300/TyMathews2024.jpg",
    "website": "https://ohiohouse.gov/members/ty-d-mathews",
    "office": "77 S. High St. 12th Floor, Columbus, OH 43215"
  },
  {
    "id": "ocd-person/392b392f-7424-4826-9f65-6b84a805473b",
    "name": "Ty Moore",
    "firstName": "Ty",
    "lastName": "Moore",
    "chamber": "lower",
    "district": "95",
    "party": "Republican",
    "email": "rep95@ohiohouse.gov",
    "phone": "614-644-8728",
    "photoUrl": "https://s3.amazonaws.com/ballotpedia-api4/files/thumbs/200/300/Ty_Moore.jpg",
    "website": "https://ohiohouse.gov/members/ty-moore",
    "office": "77 S. High St., Columbus, OH 43215"
  },
  {
    "id": "ocd-person/8b367fce-9be2-4848-837a-a475c3d531e4",
    "name": "Veronica Sims",
    "firstName": "Veronica",
    "lastName": "Sims",
    "chamber": "lower",
    "district": "33",
    "party": "Democratic",
    "email": "rep33@ohiohouse.gov",
    "phone": "614-644-6037",
    "photoUrl": "https://s3.amazonaws.com/ballotpedia-api4/files/thumbs/200/300/Veronica_Sims.jpg",
    "website": "https://ohiohouse.gov/members/veronica-r-sims",
    "office": "77 S. High St. 10th Floor, Columbus, OH 43215"
  },
  {
    "id": "ocd-person/bdc3493a-a22f-4a6b-b50e-b590216d8cfd",
    "name": "Bill DeMora",
    "firstName": "Bill",
    "lastName": "DeMora",
    "chamber": "upper",
    "district": "25",
    "party": "Democratic",
    "email": "sd25@ohiosenate.gov",
    "phone": "614-466-4583",
    "photoUrl": "https://www.legislature.ohio.gov/assets/people/william-p-demora/headshots/thumbnails/medium/william-p-demora-may-2023-headshot_medium.jpg",
    "website": "https://www.ohiosenate.gov/members/william-p-demora",
    "office": "Room 52, Statehouse, 1 Capitol Square Ground Floor, Columbus, OH 43215"
  },
  {
    "id": "ocd-person/23c443b0-e2f7-4c7a-af1e-d67d7aa366ce",
    "name": "Willis Blackshear",
    "firstName": "Willis",
    "lastName": "Blackshear",
    "chamber": "upper",
    "district": "6",
    "party": "Democratic",
    "email": "sd06@ohiosenate.gov",
    "phone": "614-466-4538",
    "photoUrl": "https://www.legislature.ohio.gov/assets/people/willis-e-blackshear-jr/headshots/thumbnails/medium/willis-e-blackshear-jr-january-2023-headshot_medium.jpg",
    "website": "https://ohiohouse.gov/members/willis-e-blackshear-jr",
    "office": "Room 49, Statehouse, 1 Capitol Square Ground Floor, Columbus, OH 43215"
  }
]